Assignment-1/A1Q1_one_bit_full_adder.v
module one_bit_full_adder (a, b, carry_in, opcode, sum, carry_out);

   input wire a;
   input wire b;
   input wire carry_in;
   input wire opcode;
   
   output wire sum;
   output wire carry_out;

   assign sum =  a ^ (opcode^b) ^ carry_in;
   assign carry_out = (a & (opcode^b)) | ((opcode^b) & carry_in) | (a & carry_in);

endmodule

Assignment-1/A1Q1_eight_bit_adder.v
`include "A1Q1_one_bit_full_adder.v"

module eight_bit_adder (x, y, opcode, sum, carry_out);

   input signed wire [7:0] x;
   input signed wire [7:0] y;
   input wire       opcode;

   output signed wire [7:0] sum;
   output wire       carry_out;

   wire [6:0] carry_over;

   one_bit_full_adder FA0 (x[0], y[0], opcode, opcode, sum[0]^1, carry_over[0]);
   one_bit_full_adder FA1 (x[1], y[1], carry_over[0], opcode, sum[1], carry_over[1]);
   one_bit_full_adder FA2 (x[2], y[2], carry_over[1], opcode, sum[2], carry_over[2]);
   one_bit_full_adder FA3 (x[3], y[3], carry_over[2], opcode, sum[3], carry_over[3]);
   one_bit_full_adder FA4 (x[4], y[4], carry_over[3], opcode, sum[4], carry_over[4]);
   one_bit_full_adder FA5 (x[5], y[5], carry_over[4], opcode, sum[5], carry_over[5]);
   one_bit_full_adder FA6 (x[6], y[6], carry_over[5], opcode, sum[6], carry_over[6]);
   one_bit_full_adder FA7 (x[7], y[7], carry_over[6], opcode, sum[7], carry_out);


endmodule

Assignment-1/A1Q1_eight_bit_adder_top.v
`include "A1Q1_eight_bit_adder.v"
module eight_bit_adder_top;

   reg [7:0] A;
   reg [7:0] B;
   reg carry_in;

   wire [7:0] sum;
   wire carry_out;

   eight_bit_adder ADDER (A, B, carry_in, sum, carry_out);
   
   integer sumi;
   always @( sum )
    sumi = sum;
   
   initial begin
       $dumpfile("A1Q1_eight_bit_adder_top.vcd");
       $dumpvars(1, eight_bit_adder_top);
       $monitor("<%g>: A=%b, B=%b, Carry_in = %b, Sum= %d, Carry_out=%b", $time, A, B, carry_in, sumi, carry_out);
       #5 A=0; B=0; carry_in=0;
         
         
       #5 A=1; B=0; carry_in=0;
         
         
       #5 A=0; B=1; carry_in=1;
         
         
       #5 A=1; B=1; carry_in=0;
         
         
       #5 A=128; B=128; carry_in=1;
         
         
       #5 A=250; B=250; carry_in=0;
         
         
       #5 A=40; B=40; carry_in=1;
         
         
       #5 A=0; B=128; carry_in=0;
         
         
       #5 A=255; B=0; carry_in=1;
         
         
       #5 A=30; B=0; carry_in=0;
         
         
       #5 A=40; B=6; carry_in=0;
         
         
       #5 A=200; B=200; carry_in=1;
         
         
       #5 A=40; B=20; carry_in=1;
         
         
       #5 A=220; B=250; carry_in=1;
         
         
       #5 A=1; B=2; carry_in=1;
         
         
   end

endmodule

Assignment-1/A1Q1_eight_bit_adder_top.vcd
$date
	Mon Jan 24 15:17:07 2022
$end
$version
	Icarus Verilog
$end
$timescale
	1s
$end
$scope module eight_bit_adder_top $end
$var wire 8 ! sum [7:0] $end
$var wire 1 " carry_out $end
$var reg 8 # A [7:0] $end
$var reg 8 $ B [7:0] $end
$var reg 1 % carry_in $end
$var integer 32 & sumi [31:0] $end
$upscope $end
$enddefinitions $end
#0
$dumpvars
bx &
x%
bx $
bx #
x"
bx !
$end
#5
b0 &
0"
b0 !
0%
b0 $
b0 #
#10
b1 &
b1 !
b1 #
#15
b10 &
b10 !
1%
b1 $
b0 #
#20
b10 &
b10 !
0%
b1 #
#25
1"
b1 &
b1 !
1%
b10000000 $
b10000000 #
#30
b11110100 &
b11110100 !
0%
b11111010 $
b11111010 #
#35
0"
b1010001 &
b1010001 !
1%
b101000 $
b101000 #
#40
b10000000 &
b10000000 !
0%
b10000000 $
b0 #
#45
1"
b0 &
b0 !
1%
b0 $
b11111111 #
#50
0"
b11110 &
b11110 !
0%
b11110 #
#55
b101110 &
b101110 !
b110 $
b101000 #
#60
1"
b10010001 &
b10010001 !
1%
b11001000 $
b11001000 #
#65
b111101 &
0"
b111101 !
b10100 $
b101000 #
#70
b11010111 &
1"
b11010111 !
b11111010 $
b11011100 #
#75
b100 &
0"
b100 !
b10 $
b1 #
